<?xml version="1.0" encoding="UTF-8"?>

<Observation xmlns="http://hl7.org/fhir">
  <id value="agrosus-resultado-colinesterase-basal-exemplo"/>
  <meta>
    <profile value="https://jefersonrl.github.io/AgroSUS-FHIR/StructureDefinition/agrosus-resultado-laboratorial"/>
  </meta>
  <language value="pt-BR"/>
  <text>
    <status value="generated"/><div xmlns="http://www.w3.org/1999/xhtml" xml:lang="pt-BR" lang="pt-BR"><p class="res-header-id"><b>Narrativa gerada: Observation agrosus-resultado-colinesterase-basal-exemplo</b></p><a name="agrosus-resultado-colinesterase-basal-exemplo"> </a><a name="hcagrosus-resultado-colinesterase-basal-exemplo"> </a><div style="display: inline-block; background-color: #d9e0e7; padding: 6px; margin: 4px; border: 1px solid #8da1b4; border-radius: 5px; line-height: 60%"><p style="margin-bottom: 0px">Língua: pt-BR</p><p style="margin-bottom: 0px">Perfil: <a href="StructureDefinition-agrosus-resultado-laboratorial.html">Resultado Laboratorial AgroSUS</a></p></div><p><b>identifier</b>: <code>https://jefersonrl.github.io/AgroSUS-FHIR/sid/resultado-laboratorial</code>/RES-LAB-2024-000001-COLIN-BASAL</p><p><b>basedOn</b>: <a href="ServiceRequest-agrosus-solicitacao-colinesterase-basal-exemplo.html">ServiceRequest Cholinesterase [Enzymatic activity/volume] in Serum or Plasma and Erythrocytes</a></p><p><b>status</b>: Final</p><p><b>category</b>: <span title="Códigos:{http://terminology.hl7.org/CodeSystem/observation-category laboratory}">Laboratory</span></p><p><b>code</b>: <span title="Códigos:{http://loinc.org 2099-0}">Colinesterase plasmática</span></p><p><b>subject</b>: <a href="Patient-agrosus-patient-example.html">Maria Aparecida de Souza</a></p><p><b>effective</b>: 2024-01-15 07:30:00-0300</p><p><b>issued</b>: 2024-01-15 14:00:00-0300</p><p><b>performer</b>: <a href="Organization-agrosus-laboratorio-exemplo.html">Laboratório Municipal de Referência — Exemplo AgroSUS</a></p><p><b>value</b>: 8200 U/L<span style="background: LightGoldenRodYellow"> (Detalhes: UCUM códigoU/L = 'U/L')</span></p><p><b>interpretation</b>: <span title="Códigos:{http://terminology.hl7.org/CodeSystem/v3-ObservationInterpretation N}">Normal</span></p><p><b>note</b>: </p><blockquote><div><p>Valor basal (pré-ocupacional), obtido antes do início do manuseio de organofosforados/carbamatos. Referência para o cálculo do percentual de inibição dos resultados subsequentes (DT-2).</p>
</div></blockquote></div>
  </text>
  <identifier>
    <system value="https://jefersonrl.github.io/AgroSUS-FHIR/sid/resultado-laboratorial"/>
    <value value="RES-LAB-2024-000001-COLIN-BASAL"/>
  </identifier>
  <basedOn>
    <reference value="ServiceRequest/agrosus-solicitacao-colinesterase-basal-exemplo"/>
  </basedOn>
  <status value="final"/>
  <category>
    <coding>
      <system value="http://terminology.hl7.org/CodeSystem/observation-category"/>
      <code value="laboratory"/>
      <display value="Laboratory"/>
    </coding>
  </category>
  <code>
    <coding>
      <system value="http://loinc.org"/>
      <code value="2099-0"/>
      <display value="Cholinesterase [Enzymatic activity/volume] in Serum or Plasma"/>
    </coding>
    <text value="Colinesterase plasmática"/>
  </code>
  <subject>
    <reference value="Patient/agrosus-patient-example"/>
    <display value="Maria Aparecida de Souza"/>
  </subject>
  <effectiveDateTime value="2024-01-15T07:30:00-03:00"/>
  <issued value="2024-01-15T14:00:00-03:00"/>
  <performer>
    <reference value="Organization/agrosus-laboratorio-exemplo"/>
    <display value="Laboratório Municipal de Referência — Exemplo AgroSUS"/>
  </performer>
  <valueQuantity>
    <value value="8200"/>
    <unit value="U/L"/>
    <system value="http://unitsofmeasure.org"/>
    <code value="U/L"/>
  </valueQuantity>
  <interpretation>
    <coding>
      <system value="http://terminology.hl7.org/CodeSystem/v3-ObservationInterpretation"/>
      <code value="N"/>
      <display value="Normal"/>
    </coding>
  </interpretation>
  <note>
    <text value="Valor basal (pré-ocupacional), obtido antes do início do manuseio de organofosforados/carbamatos. Referência para o cálculo do percentual de inibição dos resultados subsequentes (DT-2)."/>
  </note>
</Observation>